rpdvalidator/__init__.py
rpdvalidator/jsonpath_utils.py
rpdvalidator/main.py
rpdvalidator/validate.py
rpdvalidator/schema_versions/__init__.py
rpdvalidator/schema_versions/0.0.36/ASHRAE229.schema.json
rpdvalidator/schema_versions/0.0.36/ASHRAE229_extra.schema.json
rpdvalidator/schema_versions/0.0.36/Enumerations2019ASHRAE901.schema.json
rpdvalidator/schema_versions/0.0.36/Enumerations2019T24.schema.json
rpdvalidator/schema_versions/0.0.36/EnumerationsRESNET.schema.json
rpdvalidator/schema_versions/0.0.36/Output2019ASHRAE901.schema.json
rpdvalidator/schema_versions/0.0.37/ASHRAE229.schema.json
rpdvalidator/schema_versions/0.0.37/ASHRAE229_extra.schema.json
rpdvalidator/schema_versions/0.0.37/Enumerations2019ASHRAE901.schema.json
rpdvalidator/schema_versions/0.0.37/Enumerations2019T24.schema.json
rpdvalidator/schema_versions/0.0.37/EnumerationsRESNET.schema.json
rpdvalidator/schema_versions/0.0.37/Output2019ASHRAE901.schema.json
rpdvalidator/schema_versions/0.1.0/ASHRAE229.schema.json
rpdvalidator/schema_versions/0.1.0/ASHRAE229_extra.schema.json
rpdvalidator/schema_versions/0.1.0/Enumerations2019ASHRAE901.schema.json
rpdvalidator/schema_versions/0.1.0/Enumerations2019T24.schema.json
rpdvalidator/schema_versions/0.1.0/EnumerationsRESNET.schema.json
rpdvalidator/schema_versions/0.1.0/Output2019ASHRAE901.schema.json
rpdvalidator/schema_versions/0.1.1/ASHRAE229.schema.json
rpdvalidator/schema_versions/0.1.1/ASHRAE229_extra.schema.json
rpdvalidator/schema_versions/0.1.1/Enumerations2019ASHRAE901.schema.json
rpdvalidator/schema_versions/0.1.1/Enumerations2019T24.schema.json
rpdvalidator/schema_versions/0.1.1/EnumerationsRESNET.schema.json
rpdvalidator/schema_versions/0.1.1/Output2019ASHRAE901.schema.json
rpdvalidator/schema_versions/0.1.2/ASHRAE229.schema.json
rpdvalidator/schema_versions/0.1.2/ASHRAE229_extra.schema.json
rpdvalidator/schema_versions/0.1.2/Enumerations2019ASHRAE901.schema.json
rpdvalidator/schema_versions/0.1.2/Enumerations2019T24.schema.json
rpdvalidator-1.1.1.dist-info/licenses/LICENSE
rpdvalidator-1.1.1.dist-info/METADATA
rpdvalidator-1.1.1.dist-info/WHEEL
rpdvalidator-1.1.1.dist-info/entry_points.txt
rpdvalidator-1.1.1.dist-info/top_level.txt
rpdvalidator-1.1.1.dist-info/RECORD
