Metadata-Version: 2.4
Name: rpdvalidator
Version: 1.1.1
Summary: A Python tool for validating RPD files according to a specified version of the ASHRAE 229 schema.
Home-page: https://github.com/Karpman-Consulting/RECI-RPDValidator
Author: Jackson Jarboe
Author-email: jackson@karpmanconsulting.net
License: MIT
Classifier: Programming Language :: Python :: 3
Classifier: License :: OSI Approved :: MIT License
Classifier: Operating System :: OS Independent
Requires-Python: >=3.7
License-File: LICENSE
Requires-Dist: jsonpath-ng
Requires-Dist: jsonschema
Requires-Dist: referencing
Dynamic: author
Dynamic: author-email
Dynamic: classifier
Dynamic: description
Dynamic: description-content-type
Dynamic: home-page
Dynamic: license
Dynamic: license-file
Dynamic: requires-dist
Dynamic: requires-python
Dynamic: summary
